{"__type__":"cc.SpriteAtlas","_spriteFrames":{"ui_JC_3":{"__uuid__":"2cSelI7ptBYrkBel/rwWeR"},"ui_JC_4":{"__uuid__":"5dn904S6NNSK4BosfoFY3V"},"ui_JC_6":{"__uuid__":"0evNhkq1xBE7IrLrljRCP6"},"ui_HuaYuan_ZL_Qian":{"__uuid__":"0dEGpuT7JP/oWQEL2S9YEL"},"ui_JC_5":{"__uuid__":"46ur8qsnxGfpgr265Nw9wP"},"ui_HuaYuan_ZL_Qian_1":{"__uuid__":"59mYnv0etKa5x0ll7ca5/c"},"ui_JC_1":{"__uuid__":"83xaLgv3xLypklnAoJakzr"},"ui_JC_2":{"__uuid__":"94VDv9FZpLmKh+nYBekPm5"},"ui_ShuiChan_1":{"__uuid__":"03v733EKlMbbjoRVT8oW/9"},"ui_ChuShou":{"__uuid__":"55CWNnyiVGZY8kqEjznol7"},"ui_GuoYuan_1":{"__uuid__":"ebWm2CzOhNQ4jz2/F1sP0h"},"ui_ChuShou1":{"__uuid__":"b9apU3+v5NK6DR7uc9HC6M"},"ui_GuoYuan_1_1":{"__uuid__":"fbukToibtOo4lPQx/EYydL"},"ui_SC_FuBiao":{"__uuid__":"9fZrLZZL9MpaZsCriePcV/"},"ui_HuaYuan_ZL_Hou_1":{"__uuid__":"44m3lchSZPx66poCK/WIKe"},"ui_HuaYuan_ZL_Hou":{"__uuid__":"7dxfnx/ulIpqUPrVwAzOyB"},"ui_TianDi_3":{"__uuid__":"70DvVJ7OtJ/K5EgAe5aUGq"},"ui_TianDi_4_1":{"__uuid__":"58SNO5T7hAQ50+9AvqZ8TI"},"ui_TianDi_4":{"__uuid__":"d5zsGrQdRMDIIw3icheQix"},"ui_TianDi_2_1":{"__uuid__":"25mM+to4ZCI5Y+8kZ+j8g3"},"ui_TianDi_1":{"__uuid__":"8cPbLueQxJ4r9Z2tvLMUi/"},"ui_TianDi_1_1":{"__uuid__":"b1hXj6PjBBa4zGuhkuOfOU"},"ui_TianDi_2":{"__uuid__":"d1TZwvP59JyZm+bbSO6EMd"},"ui_TianDi_3_1":{"__uuid__":"d2wa+HPOpOFL7/ju3RBjXz"},"ui_ChuShou2":{"__uuid__":"d0nscFe1xO5KDDlrccHTvm"}}}